[{"domain": "www.zhihu.com", "secure": false, "value": "8605c5a961285724a313ad9c1bbbc186", "expiry": 1546420599, "path": "/", "httpOnly": false, "name": "tgw_l7_route"}, {"domain": ".zhihu.com", "secure": false, "value": "77e5f660-5c24-4296-80f0-54ef1acba30b", "expiry": 1609491699, "path": "/", "httpOnly": false, "name": "_zap"}, {"domain": ".zhihu.com", "secure": false, "value": "pSbgyOioLpVSf2W1QkHxXOJk2DSejvMI", "expiry": 1624179699, "path": "/", "httpOnly": false, "name": "_xsrf"}, {"domain": ".zhihu.com", "secure": false, "value": "\"ABDhIa6Gww6PTj75PEhgBIJy1Mb6SGj6mk8=|1546419702\"", "expiry": 1641027702, "path": "/", "httpOnly": false, "name": "d_c0"}, {"domain": ".zhihu.com", "secure": false, "value": "\"2|1:0|10:1546419702|14:capsion_ticket|44:OTBhMDk3YWJiMDVmNDI2M2IyNjlkYWRhZjgxZmJmZWY=|21b948dfc1829615de848bd239b4c7aca4a9454b7c14439d3e30c02288e6f960\"", "expiry": 1549011702, "path": "/", "httpOnly": true, "name": "capsion_ticket"}, {"domain": ".zhihu.com", "secure": false, "value": "\"2|1:0|10:1546419708|4:z_c0|92:Mi4xNlZUN0J3QUFBQUFBb0tBR3JvYkREaVlBQUFCZ0FsVk5fTXNaWFFBbFcySEc2MDBYX1BDR3JCRm1FdFdxYmRQY2lB|a6dc76ea6d8ed2b500aae74177b39c401c8cced18e364582ac1e532039598383\"", "expiry": 1561971708, "path": "/", "httpOnly": true, "name": "z_c0"}, {"domain": ".zhihu.com", "secure": false, "value": "r", "expiry": 1549011712, "path": "/", "httpOnly": false, "name": "tst"}]